naobot/agent.py
naobot/behavior.py
naobot/kinematics.py
naobot/sensors.py
naobot/__init__.py
naobot/config/robotInfo.cfg
naobot/vision/detectors.py
naobot/vision/image.py
naobot/vision/__init__.py
naobot/world_model/model.py
naobot/world_model/objects.py
naobot/world_model/__init__.py
naobot-0.1.1.dist-info/DESCRIPTION.rst
naobot-0.1.1.dist-info/METADATA
naobot-0.1.1.dist-info/metadata.json
naobot-0.1.1.dist-info/pbr.json
naobot-0.1.1.dist-info/RECORD
naobot-0.1.1.dist-info/top_level.txt
naobot-0.1.1.dist-info/WHEEL
