Metadata-Version: 2.0
Name: naobot
Version: 0.1.1
Summary: Control of a Nao robot
Home-page: https://readthedocs.org/builds/naobot
Author: Astrid Jackson
Author-email: ajackons@eecs.ucf.edu
License: MIT
Download-URL: https://github.com/evenmarbles/naobot
Keywords: NAO robot
Platform: UNKNOWN
Classifier: Development Status :: 2 - Pre-Alpha
Classifier: Intended Audience :: Developers
Classifier: License :: OSI Approved :: MIT License
Classifier: Natural Language :: English
Classifier: Programming Language :: Python :: 2
Classifier: Programming Language :: Python :: 2.7
Requires-Dist: numpy
Requires-Dist: Pillow
Requires-Dist: mlpy
